taskwarrior_subtask_capsule/__init__.py
taskwarrior_subtask_capsule/capsule.py
taskwarrior_subtask_capsule-0.2.5.dist-info/LICENSE
taskwarrior_subtask_capsule-0.2.5.dist-info/METADATA
taskwarrior_subtask_capsule-0.2.5.dist-info/WHEEL
taskwarrior_subtask_capsule-0.2.5.dist-info/entry_points.txt
taskwarrior_subtask_capsule-0.2.5.dist-info/top_level.txt
taskwarrior_subtask_capsule-0.2.5.dist-info/RECORD
