Metadata-Version: 2.1
Name: taskwarrior-subtask-capsule
Version: 0.2.5
Summary: Easily create subtasks
Home-page: https://github.com/coddingtonbear/taskwarrior-subtask-capsule
Author: Adam Coddington
Author-email: me@adamcoddington.net
License: UNKNOWN
Platform: UNKNOWN
Classifier: License :: OSI Approved :: MIT License
Classifier: Operating System :: OS Independent
Classifier: Programming Language :: Python :: 3
Requires-Dist: taskwarrior-capsules (<=1.0,>=0.1)
Requires-Dist: taskw (<2.0,>=1.0.3)
